setup.py
getheaders/__init__.py
getheaders.egg-info/PKG-INFO
getheaders.egg-info/SOURCES.txt
getheaders.egg-info/dependency_links.txt
getheaders.egg-info/top_level.txt