Metadata-Version: 1.0
Name: getheaders
Version: 1.0
Summary: Get website Headers
Home-page: UNKNOWN
Author: Louis He
Author-email: holin@holin.net
License: MIT
Platform: any
